discfit/__init__.py
discfit/calc.py
discfit/discfit.py
discfit/main.py
discfit-0.2.1.dist-info/METADATA
discfit-0.2.1.dist-info/RECORD
discfit-0.2.1.dist-info/WHEEL
discfit-0.2.1.dist-info/entry_points.txt
discfit-0.2.1.dist-info/top_level.txt
