Metadata-Version: 2.1
Name: discfit
Version: 0.2.1
Summary: Disc permeameter fitting program
Home-page: https://github.com/sekika/discfit
Author: Katsutoshi Seki
Author-email: UNKNOWN
License: MIT
Keywords: Disc permeameter
Platform: UNKNOWN
Classifier: Development Status :: 4 - Beta
Classifier: Intended Audience :: Science/Research
Classifier: Environment :: Console
Classifier: Topic :: Scientific/Engineering
Classifier: License :: OSI Approved :: MIT License
Classifier: Programming Language :: Python
Classifier: Programming Language :: Python :: 2.7
Classifier: Programming Language :: Python :: 3
Classifier: Programming Language :: Python :: 3.6
Classifier: Programming Language :: Python :: 3.7
Classifier: Natural Language :: English
Requires-Dist: numpy
Requires-Dist: scipy
